ghidra_jupyter/__init__.py
ghidra_jupyter/dispatcher.py
ghidra_jupyter/installer.py
ghidra_jupyter-1.7.4.data/data/share/jupyter/kernels/ghidra-kotlin/kernel.css
ghidra_jupyter-1.7.4.data/data/share/jupyter/kernels/ghidra-kotlin/kernel.js
ghidra_jupyter-1.7.4.data/data/share/jupyter/kernels/ghidra-kotlin/kernel.json
ghidra_jupyter-1.7.4.data/data/share/jupyter/kernels/ghidra-kotlin/logo-16x16.png
ghidra_jupyter-1.7.4.data/data/share/jupyter/kernels/ghidra-kotlin/logo-64x64.png
ghidra_jupyter-1.7.4.data/data/share/jupyter/kernels/ghidra-kotlin/wavyline-orange.gif
ghidra_jupyter-1.7.4.data/data/share/jupyter/kernels/ghidra-kotlin/wavyline-red.gif
ghidra_jupyter-1.7.4.dist-info/METADATA
ghidra_jupyter-1.7.4.dist-info/WHEEL
ghidra_jupyter-1.7.4.dist-info/entry_points.txt
ghidra_jupyter-1.7.4.dist-info/RECORD
